noteframe/__init__.py
noteframe/custom_exception.py
noteframe/logger.py
noteframe/site.py
noteframe/youtube.py
noteframe-0.0.2.dist-info/licenses/LICENSE
noteframe-0.0.2.dist-info/METADATA
noteframe-0.0.2.dist-info/WHEEL
noteframe-0.0.2.dist-info/top_level.txt
noteframe-0.0.2.dist-info/RECORD
